Workbook

Sheet RESUMEN
B2: Finanzas personales
B4: Mes | C4: Año
B5: Abril | C5: 2026 | G5: Saldo | H5: =B8-F8 -> 565772 | AZ5: Enero
AZ6: Febrero
B7: Ingresos totales | F7: Egresos totales | AZ7: Marzo
B8: =D19 -> 2196533 | F8: =H19 -> 1630761 | AZ8: Abril
AZ9: Mayo
AZ10: Junio
B11: Resumen Ingresos | F11: Resumen Egresos | J11: Gastos del mes | N11: Deseos | R11: Ahorro | AZ11: Julio
B12: Categoria | C12: Ppto | D12: Real | F12: Categoria | G12: Ppto | H12: Real | J12: Categoria | K12: Ppto | L12: Real | N12: Categoria | O12: Ppto | P12: Real | R12: Categoria | S12: Ppto | T12: Real | AZ12: Agosto
B13: Sueldo | C13: 1800000 | D13: =SUMIFS(Registros[Ingreso],Registros[Mes],MONTH("1"&RESUMEN!$B$5),Registros[Año],C5,Registros[Busca palabra sueldo],TRUE) -> 1795336 | F13: Gastos del mes | G13: =890000+K13+K16 -> 1180000 | H13: =SUMIFS(Registros[Egreso],Registros[Mes],MONTH("1"&RESUMEN!$B$5),Registros[Año],$C$5,Registros[Categoría],F13) -> 932023 | J13: Supermercado | K13: 250000 | L13: =SUMIFS(Registros[Egreso],Registros[Mes],MONTH("1"&RESUMEN!$B$5),Registros[Año],$C$5,Registros[Categoría],$J$11,Registros[Subcategoría],J13) -> 31257 | N13: Supermercado | O13: 0 | P13: =SUMIFS(Registros[Egreso],Registros[Mes],MONTH("1"&RESUMEN!$B$5),Registros[Año],$C$5,Registros[Categoría],$N$11,Registros[Subcategoría],N13) -> 1790 | R13: Cuenta Ahorro | S13: =C19-K31-O31 -> 515000 | T13: =SUMIFS(Registros[Egreso],Registros[Mes],MONTH("1"&RESUMEN!$B$5),Registros[Año],$C$5,Registros[Categoría],$R$11,Registros[Subcategoría],R13) -> 6814 | AZ13: Septiembre
B14: Depósitos Javi | C14: 360000 | D14: =SUMIFS(Registros[Ingreso],Registros[Mes],MONTH("1"&RESUMEN!$B$5),Registros[Año],C5,Registros[Busca palabra Javi],TRUE) -> 360000 | F14: Deseos | G14: =O31 -> 465000 | H14: =SUMIFS(Registros[Egreso],Registros[Mes],MONTH("1"&RESUMEN!$B$5),Registros[Año],$C$5,Registros[Categoría],F14) -> 691924 | J14: Cuentas | K14: =70000+120000 -> 190000 | L14: =SUMIFS(Registros[Egreso],Registros[Mes],MONTH("1"&RESUMEN!$B$5),Registros[Año],$C$5,Registros[Categoría],$J$11,Registros[Subcategoría],J14) -> 150133 | N14: Cuentas | O14: 0 | P14: =SUMIFS(Registros[Egreso],Registros[Mes],MONTH("1"&RESUMEN!$B$5),Registros[Año],$C$5,Registros[Categoría],$N$11,Registros[Subcategoría],N14) -> 6000 | S14: 0 | AZ14: Octubre
B15: Otro depósitos | C15: 0 | D15: =SUMIFS(Registros[Ingreso],Registros[Mes],MONTH("1"&RESUMEN!$B$5),Registros[Año],C5,Registros[Busca palabra sueldo],FALSE,Registros[Busca palabra Javi],FALSE) -> 41197 | F15: Ahorro | G15: =S19 -> 515000 | H15: =SUMIFS(Registros[Egreso],Registros[Mes],MONTH("1"&RESUMEN!$B$5),Registros[Año],$C$5,Registros[Categoría],F15) -> 6814 | J15: Arriendo | K15: 700000 | L15: =SUMIFS(Registros[Egreso],Registros[Mes],MONTH("1"&RESUMEN!$B$5),Registros[Año],$C$5,Registros[Categoría],$J$11,Registros[Subcategoría],J15) -> 700000 | N15: Arriendo | O15: 0 | P15: =SUMIFS(Registros[Egreso],Registros[Mes],MONTH("1"&RESUMEN!$B$5),Registros[Año],$C$5,Registros[Categoría],$N$11,Registros[Subcategoría],N15) -> 0 | S15: 0 | AZ15: Noviembre
C16: 0 | D16: 0 | G16: 0 | H16: =SUMIFS(Registros[Egreso],Registros[Mes],MONTH("1"&RESUMEN!$B$5),Registros[Año],$C$5,Registros[Categoría],F16) -> 0 | J16: Transporte | K16: 40000 | L16: =SUMIFS(Registros[Egreso],Registros[Mes],MONTH("1"&RESUMEN!$B$5),Registros[Año],$C$5,Registros[Categoría],$J$11,Registros[Subcategoría],J16) -> 10000 | N16: Transporte | O16: 0 | P16: =SUMIFS(Registros[Egreso],Registros[Mes],MONTH("1"&RESUMEN!$B$5),Registros[Año],$C$5,Registros[Categoría],$N$11,Registros[Subcategoría],N16) -> 0 | S16: 0 | AZ16: Diciembre
C17: 0 | D17: 0 | G17: 0 | H17: =SUMIFS(Registros[Egreso],Registros[Mes],MONTH("1"&RESUMEN!$B$5),Registros[Año],$C$5,Registros[Categoría],F17) -> 0 | J17: Deudas | K17: 0 | L17: =SUMIFS(Registros[Egreso],Registros[Mes],MONTH("1"&RESUMEN!$B$5),Registros[Año],$C$5,Registros[Categoría],$J$11,Registros[Subcategoría],J17) -> 0 | N17: Deudas | O17: 0 | P17: =SUMIFS(Registros[Egreso],Registros[Mes],MONTH("1"&RESUMEN!$B$5),Registros[Año],$C$5,Registros[Categoría],$N$11,Registros[Subcategoría],N17) -> 0 | S17: 0
C18: 0 | D18: 0 | G18: 0 | H18: =SUMIFS(Registros[Egreso],Registros[Mes],MONTH("1"&RESUMEN!$B$5),Registros[Año],$C$5,Registros[Categoría],F18) -> 0 | J18: Ropa | K18: 0 | L18: =SUMIFS(Registros[Egreso],Registros[Mes],MONTH("1"&RESUMEN!$B$5),Registros[Año],$C$5,Registros[Categoría],$J$11,Registros[Subcategoría],J18) -> 0 | N18: Ropa | P18: =SUMIFS(Registros[Egreso],Registros[Mes],MONTH("1"&RESUMEN!$B$5),Registros[Año],$C$5,Registros[Categoría],$N$11,Registros[Subcategoría],N18) -> 0 | S18: 0
B19: Total | C19: =SUM(C13:C18) -> 2160000 | D19: =SUM(D13:D18) -> 2196533 | F19: Total | G19: =SUM(G13:G18) -> 2160000 | H19: =SUM(H13:H18) -> 1630761 | J19: Efectivo | K19: 0 | L19: =SUMIFS(Registros[Egreso],Registros[Mes],MONTH("1"&RESUMEN!$B$5),Registros[Año],$C$5,Registros[Categoría],$J$11,Registros[Subcategoría],J19) -> 0 | N19: Efectivo | O19: 0 | P19: =SUMIFS(Registros[Egreso],Registros[Mes],MONTH("1"&RESUMEN!$B$5),Registros[Año],$C$5,Registros[Categoría],$N$11,Registros[Subcategoría],N19) -> 0 | R19: Total | S19: =SUM(S13:S18) -> 515000 | T19: =SUM(T13:T18) -> 6814
J20: Salida a comer | K20: 0 | L20: =SUMIFS(Registros[Egreso],Registros[Mes],MONTH("1"&RESUMEN!$B$5),Registros[Año],$C$5,Registros[Categoría],$J$11,Registros[Subcategoría],J20) -> 4600 | N20: Salida a comer | O20: 0 | P20: =SUMIFS(Registros[Egreso],Registros[Mes],MONTH("1"&RESUMEN!$B$5),Registros[Año],$C$5,Registros[Categoría],$N$11,Registros[Subcategoría],N20) -> 30000
J21: Comida | K21: 0 | L21: =SUMIFS(Registros[Egreso],Registros[Mes],MONTH("1"&RESUMEN!$B$5),Registros[Año],$C$5,Registros[Categoría],$J$11,Registros[Subcategoría],J21) -> 0 | N21: Comida | O21: 0 | P21: =SUMIFS(Registros[Egreso],Registros[Mes],MONTH("1"&RESUMEN!$B$5),Registros[Año],$C$5,Registros[Categoría],$N$11,Registros[Subcategoría],N21) -> 0
J22: Escalada | K22: 0 | L22: =SUMIFS(Registros[Egreso],Registros[Mes],MONTH("1"&RESUMEN!$B$5),Registros[Año],$C$5,Registros[Categoría],$J$11,Registros[Subcategoría],J22) -> 0 | N22: Escalada | O22: 55000 | P22: =SUMIFS(Registros[Egreso],Registros[Mes],MONTH("1"&RESUMEN!$B$5),Registros[Año],$C$5,Registros[Categoría],$N$11,Registros[Subcategoría],N22) -> 55000
J23: Carrete | K23: 0 | L23: =SUMIFS(Registros[Egreso],Registros[Mes],MONTH("1"&RESUMEN!$B$5),Registros[Año],$C$5,Registros[Categoría],$J$11,Registros[Subcategoría],J23) -> 0 | N23: Carrete | O23: 0 | P23: =SUMIFS(Registros[Egreso],Registros[Mes],MONTH("1"&RESUMEN!$B$5),Registros[Año],$C$5,Registros[Categoría],$N$11,Registros[Subcategoría],N23) -> 67710
J24: Regalos | K24: 0 | L24: =SUMIFS(Registros[Egreso],Registros[Mes],MONTH("1"&RESUMEN!$B$5),Registros[Año],$C$5,Registros[Categoría],$J$11,Registros[Subcategoría],J24) -> 0 | N24: Regalos | O24: 30000 | P24: =SUMIFS(Registros[Egreso],Registros[Mes],MONTH("1"&RESUMEN!$B$5),Registros[Año],$C$5,Registros[Categoría],$N$11,Registros[Subcategoría],N24) -> 70496
J25: Auto | K25: 0 | L25: =SUMIFS(Registros[Egreso],Registros[Mes],MONTH("1"&RESUMEN!$B$5),Registros[Año],$C$5,Registros[Categoría],$J$11,Registros[Subcategoría],J25) -> 0 | N25: Auto | O25: 30000 | P25: =SUMIFS(Registros[Egreso],Registros[Mes],MONTH("1"&RESUMEN!$B$5),Registros[Año],$C$5,Registros[Categoría],$N$11,Registros[Subcategoría],N25) -> 0
J26: Equipo escalada | K26: 0 | L26: =SUMIFS(Registros[Egreso],Registros[Mes],MONTH("1"&RESUMEN!$B$5),Registros[Año],$C$5,Registros[Categoría],$J$11,Registros[Subcategoría],J26) -> 0 | N26: Equipo escalada | O26: 0 | P26: =SUMIFS(Registros[Egreso],Registros[Mes],MONTH("1"&RESUMEN!$B$5),Registros[Año],$C$5,Registros[Categoría],$N$11,Registros[Subcategoría],N26) -> 0
J27: Salud | K27: 0 | L27: =SUMIFS(Registros[Egreso],Registros[Mes],MONTH("1"&RESUMEN!$B$5),Registros[Año],$C$5,Registros[Categoría],$J$11,Registros[Subcategoría],J27) -> 36033 | N27: Salud | O27: 0 | P27: =SUMIFS(Registros[Egreso],Registros[Mes],MONTH("1"&RESUMEN!$B$5),Registros[Año],$C$5,Registros[Categoría],$N$11,Registros[Subcategoría],N27) -> 0
J28: Compras dpto | K28: 0 | L28: =SUMIFS(Registros[Egreso],Registros[Mes],MONTH("1"&RESUMEN!$B$5),Registros[Año],$C$5,Registros[Categoría],$J$11,Registros[Subcategoría],J28) -> 0 | N28: Compras dpto | O28: 350000 | P28: =SUMIFS(Registros[Egreso],Registros[Mes],MONTH("1"&RESUMEN!$B$5),Registros[Año],$C$5,Registros[Categoría],$N$11,Registros[Subcategoría],N28) -> 366152
J29: Productos varios | K29: 0 | L29: =SUMIFS(Registros[Egreso],Registros[Mes],MONTH("1"&RESUMEN!$B$5),Registros[Año],$C$5,Registros[Categoría],$J$11,Registros[Subcategoría],J29) -> 0 | N29: Productos varios | P29: =SUMIFS(Registros[Egreso],Registros[Mes],MONTH("1"&RESUMEN!$B$5),Registros[Año],$C$5,Registros[Categoría],$N$11,Registros[Subcategoría],N29) -> 0
J30: Otros | K30: 0 | L30: =SUMIFS(Registros[Egreso],Registros[Mes],MONTH("1"&RESUMEN!$B$5),Registros[Año],$C$5,Registros[Categoría],$J$11,Registros[Subcategoría],J30) -> 0 | N30: Otros | O30: 0 | P30: =SUMIFS(Registros[Egreso],Registros[Mes],MONTH("1"&RESUMEN!$B$5),Registros[Año],$C$5,Registros[Categoría],$N$11,Registros[Subcategoría],N30) -> 18707
J31: Total | K31: =SUM(K13:K30) -> 1180000 | L31: =SUM(L13:L30) -> 932023 | N31: Total | O31: =SUM(O13:O30) -> 465000 | P31: =SUM(P13:P30) -> 615855

Sheet Inversiones
B2: Fondo compra departamento
B3: Plataforma | C3: Fondo | D3: Monto inversión | E3: Monto actual | F3: Rentabilidad | G3: % Rentabilidad
B4: XTB | C4: Departamento | D4: 200000 | E4: 230294 | F4: =E4-D4 -> 30294 | G4: =F4/D4 -> 0.15147
B5: Fintual | C5: Departamento | D5: 637388 | E5: 698147 | F5: =E5-D5 -> 60759 | G5: =F5/D5 -> 0.095324983
B6: Fraccional | C6: Departamento | D6: 190000 | E6: 249398 | F6: =E6-D6 -> 59398 | G6: =F6/D6 -> 0.31262105
B7: Cumplo | C7: Departamento | D7: 300000 | E7: =102414+216164 -> 318578 | F7: =E7-D7 -> 18578 | G7: =F7/D7 -> 0.061926667
B8: Mercadopago | C8: Departamento | D8: =600000+3423351 -> 4023351 | E8: 4023555 | F8: =E8-D8 -> 204 | G8: =F8/D8 -> 5.0704003e-05
C10: Total | D10: =SUM(D4:D8) -> 5350739 | E10: =SUM(E4:E8) -> 5519972 | F10: =SUM(F4:F8) -> 169233 | G10: =AVERAGE(G4:G8) -> 0.12427868
B12: Fondo Jubilación
B13: Plataforma | C13: Fondo | D13: Monto inversión | E13: Monto actual | F13: Rentabilidad | G13: % Rentabilidad
B14: Buda Bitcoins | C14: Jubilación | D14: 100000 | E14: 66987 | F14: =E14-D14 -> -33013 | G14: =F14/D14 -> -0.33013
B15: Buda Ethereum | C15: Jubilación | D15: 100000 | E15: 75083 | F15: =E15-D15 -> -24917 | G15: =F15/D15 -> -0.24917
C17: Total | D17: =SUM(D14:D16) -> 200000 | E17: =SUM(E14:E16) -> 142070 | F17: =SUM(F14:F16) -> -57930 | G17: =AVERAGE(G14:G16) -> -0.28965

Sheet Registros
B2: Registros | W2: Categorias | X2: Subcategorias
B3: Fecha | C3: Descripción | D3: Categoría | E3: Subcategoría | F3: Ingreso | G3: Egreso | H3: Mes | I3: Año | J3: Busca palabra sueldo | K3: Busca palabra Javi | W3: Gastos del mes | X3: Supermercado
B4: 46082 | C4: Sueldo marzo | D4: Gastos del mes | F4: 1795407 | H4: =MONTH(Registros[[#This Row],[Fecha]]) -> 3 | I4: =YEAR(Registros[[#This Row],[Fecha]]) -> 2026 | J4: =OR(ISNUMBER(FIND("Sueldo",Registros[[#This Row],[Descripción]])),ISNUMBER(FIND("sueldo",Registros[[#This Row],[Descripción]]))) -> TRUE | K4: =OR(ISNUMBER(FIND("Javi",Registros[[#This Row],[Descripción]])),ISNUMBER(FIND("javi",Registros[[#This Row],[Descripción]]))) -> FALSE | W4: Deseos | X4: Cuentas
B5: 46082 | C5: Despedida soltero Oyane (Cuota joaco) | D5: Deseos | E5: Carrete | G5: 164834 | H5: =MONTH(Registros[[#This Row],[Fecha]]) -> 3 | I5: =YEAR(Registros[[#This Row],[Fecha]]) -> 2026 | J5: =OR(ISNUMBER(FIND("Sueldo",Registros[[#This Row],[Descripción]])),ISNUMBER(FIND("sueldo",Registros[[#This Row],[Descripción]]))) -> FALSE | K5: =OR(ISNUMBER(FIND("Javi",Registros[[#This Row],[Descripción]])),ISNUMBER(FIND("javi",Registros[[#This Row],[Descripción]]))) -> FALSE | W5: Ahorro | X5: Arriendo
B6: 46082 | D6: Deseos | G6: 14400 | H6: =MONTH(Registros[[#This Row],[Fecha]]) -> 3 | I6: =YEAR(Registros[[#This Row],[Fecha]]) -> 2026 | J6: =OR(ISNUMBER(FIND("Sueldo",Registros[[#This Row],[Descripción]])),ISNUMBER(FIND("sueldo",Registros[[#This Row],[Descripción]]))) -> FALSE | K6: =OR(ISNUMBER(FIND("Javi",Registros[[#This Row],[Descripción]])),ISNUMBER(FIND("javi",Registros[[#This Row],[Descripción]]))) -> FALSE | X6: Transporte
B7: 46082 | D7: Deseos | G7: 63000 | H7: =MONTH(Registros[[#This Row],[Fecha]]) -> 3 | I7: =YEAR(Registros[[#This Row],[Fecha]]) -> 2026 | J7: =OR(ISNUMBER(FIND("Sueldo",Registros[[#This Row],[Descripción]])),ISNUMBER(FIND("sueldo",Registros[[#This Row],[Descripción]]))) -> FALSE | K7: =OR(ISNUMBER(FIND("Javi",Registros[[#This Row],[Descripción]])),ISNUMBER(FIND("javi",Registros[[#This Row],[Descripción]]))) -> FALSE | X7: Deudas
B8: 46082 | D8: Deseos | G8: 2500 | H8: =MONTH(Registros[[#This Row],[Fecha]]) -> 3 | I8: =YEAR(Registros[[#This Row],[Fecha]]) -> 2026 | J8: =OR(ISNUMBER(FIND("Sueldo",Registros[[#This Row],[Descripción]])),ISNUMBER(FIND("sueldo",Registros[[#This Row],[Descripción]]))) -> FALSE | K8: =OR(ISNUMBER(FIND("Javi",Registros[[#This Row],[Descripción]])),ISNUMBER(FIND("javi",Registros[[#This Row],[Descripción]]))) -> FALSE | X8: Ropa
B9: 46082 | C9: Depósito Gabo | D9: Deseos | F9: 7444 | H9: =MONTH(Registros[[#This Row],[Fecha]]) -> 3 | I9: =YEAR(Registros[[#This Row],[Fecha]]) -> 2026 | J9: =OR(ISNUMBER(FIND("Sueldo",Registros[[#This Row],[Descripción]])),ISNUMBER(FIND("sueldo",Registros[[#This Row],[Descripción]]))) -> FALSE | K9: =OR(ISNUMBER(FIND("Javi",Registros[[#This Row],[Descripción]])),ISNUMBER(FIND("javi",Registros[[#This Row],[Descripción]]))) -> FALSE | X9: Efectivo
B10: 46082 | C10: Compra Easy luces | D10: Gastos del mes | E10: Compras dpto | G10: 109870 | H10: =MONTH(Registros[[#This Row],[Fecha]]) -> 3 | I10: =YEAR(Registros[[#This Row],[Fecha]]) -> 2026 | J10: =OR(ISNUMBER(FIND("Sueldo",Registros[[#This Row],[Descripción]])),ISNUMBER(FIND("sueldo",Registros[[#This Row],[Descripción]]))) -> FALSE | K10: =OR(ISNUMBER(FIND("Javi",Registros[[#This Row],[Descripción]])),ISNUMBER(FIND("javi",Registros[[#This Row],[Descripción]]))) -> FALSE | X10: Salida a comer
B11: 46082 | D11: Deseos | G11: 6480 | H11: =MONTH(Registros[[#This Row],[Fecha]]) -> 3 | I11: =YEAR(Registros[[#This Row],[Fecha]]) -> 2026 | J11: =OR(ISNUMBER(FIND("Sueldo",Registros[[#This Row],[Descripción]])),ISNUMBER(FIND("sueldo",Registros[[#This Row],[Descripción]]))) -> FALSE | K11: =OR(ISNUMBER(FIND("Javi",Registros[[#This Row],[Descripción]])),ISNUMBER(FIND("javi",Registros[[#This Row],[Descripción]]))) -> FALSE | X11: Comida
B12: 46082 | C12: Uber | D12: Deseos | E12: Transporte | G12: 4000 | H12: =MONTH(Registros[[#This Row],[Fecha]]) -> 3 | I12: =YEAR(Registros[[#This Row],[Fecha]]) -> 2026 | J12: =OR(ISNUMBER(FIND("Sueldo",Registros[[#This Row],[Descripción]])),ISNUMBER(FIND("sueldo",Registros[[#This Row],[Descripción]]))) -> FALSE | K12: =OR(ISNUMBER(FIND("Javi",Registros[[#This Row],[Descripción]])),ISNUMBER(FIND("javi",Registros[[#This Row],[Descripción]]))) -> FALSE | X12: Escalada
B13: 46082 | C13: Arriendo | D13: Gastos del mes | E13: Arriendo | G13: 588166 | H13: =MONTH(Registros[[#This Row],[Fecha]]) -> 3 | I13: =YEAR(Registros[[#This Row],[Fecha]]) -> 2026 | J13: =OR(ISNUMBER(FIND("Sueldo",Registros[[#This Row],[Descripción]])),ISNUMBER(FIND("sueldo",Registros[[#This Row],[Descripción]]))) -> FALSE | K13: =OR(ISNUMBER(FIND("Javi",Registros[[#This Row],[Descripción]])),ISNUMBER(FIND("javi",Registros[[#This Row],[Descripción]]))) -> FALSE | X13: Carrete
B14: 46082 | D14: Deseos | G14: 11040 | H14: =MONTH(Registros[[#This Row],[Fecha]]) -> 3 | I14: =YEAR(Registros[[#This Row],[Fecha]]) -> 2026 | J14: =OR(ISNUMBER(FIND("Sueldo",Registros[[#This Row],[Descripción]])),ISNUMBER(FIND("sueldo",Registros[[#This Row],[Descripción]]))) -> FALSE | K14: =OR(ISNUMBER(FIND("Javi",Registros[[#This Row],[Descripción]])),ISNUMBER(FIND("javi",Registros[[#This Row],[Descripción]]))) -> FALSE | X14: Regalos
B15: 46083 | C15: Arriendo y cuentas Javi | D15: Gastos del mes | E15: Arriendo | F15: 360000 | H15: =MONTH(Registros[[#This Row],[Fecha]]) -> 3 | I15: =YEAR(Registros[[#This Row],[Fecha]]) -> 2026 | J15: =OR(ISNUMBER(FIND("Sueldo",Registros[[#This Row],[Descripción]])),ISNUMBER(FIND("sueldo",Registros[[#This Row],[Descripción]]))) -> FALSE | K15: =OR(ISNUMBER(FIND("Javi",Registros[[#This Row],[Descripción]])),ISNUMBER(FIND("javi",Registros[[#This Row],[Descripción]]))) -> TRUE | X15: Auto
B16: 46083 | C16: Compra unimarc | D16: Gastos del mes | E16: Supermercado | G16: 6770 | H16: =MONTH(Registros[[#This Row],[Fecha]]) -> 3 | I16: =YEAR(Registros[[#This Row],[Fecha]]) -> 2026 | J16: =OR(ISNUMBER(FIND("Sueldo",Registros[[#This Row],[Descripción]])),ISNUMBER(FIND("sueldo",Registros[[#This Row],[Descripción]]))) -> FALSE | K16: =OR(ISNUMBER(FIND("Javi",Registros[[#This Row],[Descripción]])),ISNUMBER(FIND("javi",Registros[[#This Row],[Descripción]]))) -> FALSE | X16: Equipo escalada
B17: 46083 | C17: Mensualidad Stargym | D17: Deseos | E17: Escalada | G17: 70000 | H17: =MONTH(Registros[[#This Row],[Fecha]]) -> 3 | I17: =YEAR(Registros[[#This Row],[Fecha]]) -> 2026 | J17: =OR(ISNUMBER(FIND("Sueldo",Registros[[#This Row],[Descripción]])),ISNUMBER(FIND("sueldo",Registros[[#This Row],[Descripción]]))) -> FALSE | K17: =OR(ISNUMBER(FIND("Javi",Registros[[#This Row],[Descripción]])),ISNUMBER(FIND("javi",Registros[[#This Row],[Descripción]]))) -> FALSE | X17: Salud
B18: 46084 | C18: Cuenta movistar | D18: Gastos del mes | E18: Cuentas | G18: 46286 | H18: =MONTH(Registros[[#This Row],[Fecha]]) -> 3 | I18: =YEAR(Registros[[#This Row],[Fecha]]) -> 2026 | J18: =OR(ISNUMBER(FIND("Sueldo",Registros[[#This Row],[Descripción]])),ISNUMBER(FIND("sueldo",Registros[[#This Row],[Descripción]]))) -> FALSE | K18: =OR(ISNUMBER(FIND("Javi",Registros[[#This Row],[Descripción]])),ISNUMBER(FIND("javi",Registros[[#This Row],[Descripción]]))) -> FALSE | X18: Compras dpto
B19: 46084 | C19: Virgin mobile | D19: Gastos del mes | E19: Cuentas | G19: 7990 | H19: =MONTH(Registros[[#This Row],[Fecha]]) -> 3 | I19: =YEAR(Registros[[#This Row],[Fecha]]) -> 2026 | J19: =OR(ISNUMBER(FIND("Sueldo",Registros[[#This Row],[Descripción]])),ISNUMBER(FIND("sueldo",Registros[[#This Row],[Descripción]]))) -> FALSE | K19: =OR(ISNUMBER(FIND("Javi",Registros[[#This Row],[Descripción]])),ISNUMBER(FIND("javi",Registros[[#This Row],[Descripción]]))) -> FALSE | X19: Productos varios
B20: 46085 | C20: Carga Bip | D20: Gastos del mes | E20: Transporte | G20: 20000 | H20: =MONTH(Registros[[#This Row],[Fecha]]) -> 3 | I20: =YEAR(Registros[[#This Row],[Fecha]]) -> 2026 | J20: =OR(ISNUMBER(FIND("Sueldo",Registros[[#This Row],[Descripción]])),ISNUMBER(FIND("sueldo",Registros[[#This Row],[Descripción]]))) -> FALSE | K20: =OR(ISNUMBER(FIND("Javi",Registros[[#This Row],[Descripción]])),ISNUMBER(FIND("javi",Registros[[#This Row],[Descripción]]))) -> FALSE | X20: Otros
B21: 46085 | C21: Almuerzo | D21: Gastos del mes | E21: Salida a comer | G21: 5700 | H21: =MONTH(Registros[[#This Row],[Fecha]]) -> 3 | I21: =YEAR(Registros[[#This Row],[Fecha]]) -> 2026 | J21: =OR(ISNUMBER(FIND("Sueldo",Registros[[#This Row],[Descripción]])),ISNUMBER(FIND("sueldo",Registros[[#This Row],[Descripción]]))) -> FALSE | K21: =OR(ISNUMBER(FIND("Javi",Registros[[#This Row],[Descripción]])),ISNUMBER(FIND("javi",Registros[[#This Row],[Descripción]]))) -> FALSE | X21: Cuenta Ahorro
B22: 46086 | C22: Regalo Thomas | D22: Deseos | E22: Regalos | G22: 38000 | H22: =MONTH(Registros[[#This Row],[Fecha]]) -> 3 | I22: =YEAR(Registros[[#This Row],[Fecha]]) -> 2026 | J22: =OR(ISNUMBER(FIND("Sueldo",Registros[[#This Row],[Descripción]])),ISNUMBER(FIND("sueldo",Registros[[#This Row],[Descripción]]))) -> FALSE | K22: =OR(ISNUMBER(FIND("Javi",Registros[[#This Row],[Descripción]])),ISNUMBER(FIND("javi",Registros[[#This Row],[Descripción]]))) -> FALSE
B23: 46086 | C23: Regalo Thomas (Tomi) | D23: Deseos | E23: Regalos | F23: 12590 | H23: =MONTH(Registros[[#This Row],[Fecha]]) -> 3 | I23: =YEAR(Registros[[#This Row],[Fecha]]) -> 2026 | J23: =OR(ISNUMBER(FIND("Sueldo",Registros[[#This Row],[Descripción]])),ISNUMBER(FIND("sueldo",Registros[[#This Row],[Descripción]]))) -> FALSE | K23: =OR(ISNUMBER(FIND("Javi",Registros[[#This Row],[Descripción]])),ISNUMBER(FIND("javi",Registros[[#This Row],[Descripción]]))) -> FALSE
B24: 46086 | D24: Deseos | G24: 5200 | H24: =MONTH(Registros[[#This Row],[Fecha]]) -> 3 | I24: =YEAR(Registros[[#This Row],[Fecha]]) -> 2026 | J24: =OR(ISNUMBER(FIND("Sueldo",Registros[[#This Row],[Descripción]])),ISNUMBER(FIND("sueldo",Registros[[#This Row],[Descripción]]))) -> FALSE | K24: =OR(ISNUMBER(FIND("Javi",Registros[[#This Row],[Descripción]])),ISNUMBER(FIND("javi",Registros[[#This Row],[Descripción]]))) -> FALSE
B25: 46087 | C25: Buffet cumple abuela Javi | D25: Deseos | E25: Salida a comer | G25: 19920 | H25: =MONTH(Registros[[#This Row],[Fecha]]) -> 3 | I25: =YEAR(Registros[[#This Row],[Fecha]]) -> 2026 | J25: =OR(ISNUMBER(FIND("Sueldo",Registros[[#This Row],[Descripción]])),ISNUMBER(FIND("sueldo",Registros[[#This Row],[Descripción]]))) -> FALSE | K25: =OR(ISNUMBER(FIND("Javi",Registros[[#This Row],[Descripción]])),ISNUMBER(FIND("javi",Registros[[#This Row],[Descripción]]))) -> TRUE
B26: 46087 | C26: Cabaña Bahia Coique (Charly + Kathy) | D26: Deseos | E26: Otros | F26: 39840 | H26: =MONTH(Registros[[#This Row],[Fecha]]) -> 3 | I26: =YEAR(Registros[[#This Row],[Fecha]]) -> 2026 | J26: =OR(ISNUMBER(FIND("Sueldo",Registros[[#This Row],[Descripción]])),ISNUMBER(FIND("sueldo",Registros[[#This Row],[Descripción]]))) -> FALSE | K26: =OR(ISNUMBER(FIND("Javi",Registros[[#This Row],[Descripción]])),ISNUMBER(FIND("javi",Registros[[#This Row],[Descripción]]))) -> FALSE
B27: 46087 | C27: Cabaña Bahia Coique (Ivan + Cami) | D27: Deseos | E27: Otros | F27: 19920 | H27: =MONTH(Registros[[#This Row],[Fecha]]) -> 3 | I27: =YEAR(Registros[[#This Row],[Fecha]]) -> 2026 | J27: =OR(ISNUMBER(FIND("Sueldo",Registros[[#This Row],[Descripción]])),ISNUMBER(FIND("sueldo",Registros[[#This Row],[Descripción]]))) -> FALSE | K27: =OR(ISNUMBER(FIND("Javi",Registros[[#This Row],[Descripción]])),ISNUMBER(FIND("javi",Registros[[#This Row],[Descripción]]))) -> FALSE
B28: 46087 | C28: Completos dominó Pool | D28: Deseos | E28: Salida a comer | G28: 31990 | H28: =MONTH(Registros[[#This Row],[Fecha]]) -> 3 | I28: =YEAR(Registros[[#This Row],[Fecha]]) -> 2026 | J28: =OR(ISNUMBER(FIND("Sueldo",Registros[[#This Row],[Descripción]])),ISNUMBER(FIND("sueldo",Registros[[#This Row],[Descripción]]))) -> FALSE | K28: =OR(ISNUMBER(FIND("Javi",Registros[[#This Row],[Descripción]])),ISNUMBER(FIND("javi",Registros[[#This Row],[Descripción]]))) -> FALSE
B29: 46087 | D29: Deseos | G29: 10000 | H29: =MONTH(Registros[[#This Row],[Fecha]]) -> 3 | I29: =YEAR(Registros[[#This Row],[Fecha]]) -> 2026 | J29: =OR(ISNUMBER(FIND("Sueldo",Registros[[#This Row],[Descripción]])),ISNUMBER(FIND("sueldo",Registros[[#This Row],[Descripción]]))) -> FALSE | K29: =OR(ISNUMBER(FIND("Javi",Registros[[#This Row],[Descripción]])),ISNUMBER(FIND("javi",Registros[[#This Row],[Descripción]]))) -> FALSE
B30: 46088 | D30: Deseos | G30: 7150 | H30: =MONTH(Registros[[#This Row],[Fecha]]) -> 3 | I30: =YEAR(Registros[[#This Row],[Fecha]]) -> 2026 | J30: =OR(ISNUMBER(FIND("Sueldo",Registros[[#This Row],[Descripción]])),ISNUMBER(FIND("sueldo",Registros[[#This Row],[Descripción]]))) -> FALSE | K30: =OR(ISNUMBER(FIND("Javi",Registros[[#This Row],[Descripción]])),ISNUMBER(FIND("javi",Registros[[#This Row],[Descripción]]))) -> FALSE
B31: 46088 | D31: Deseos | G31: 5200 | H31: =MONTH(Registros[[#This Row],[Fecha]]) -> 3 | I31: =YEAR(Registros[[#This Row],[Fecha]]) -> 2026 | J31: =OR(ISNUMBER(FIND("Sueldo",Registros[[#This Row],[Descripción]])),ISNUMBER(FIND("sueldo",Registros[[#This Row],[Descripción]]))) -> FALSE | K31: =OR(ISNUMBER(FIND("Javi",Registros[[#This Row],[Descripción]])),ISNUMBER(FIND("javi",Registros[[#This Row],[Descripción]]))) -> FALSE
B32: 46088 | C32: Regalo Thomas (Carrasco) | D32: Deseos | E32: Regalos | F32: 12590 | H32: =MONTH(Registros[[#This Row],[Fecha]]) -> 3 | I32: =YEAR(Registros[[#This Row],[Fecha]]) -> 2026 | J32: =OR(ISNUMBER(FIND("Sueldo",Registros[[#This Row],[Descripción]])),ISNUMBER(FIND("sueldo",Registros[[#This Row],[Descripción]]))) -> FALSE | K32: =OR(ISNUMBER(FIND("Javi",Registros[[#This Row],[Descripción]])),ISNUMBER(FIND("javi",Registros[[#This Row],[Descripción]]))) -> FALSE
B33: 46089 | C33: Carga bencina | D33: Gastos del mes | E33: Auto | G33: 20000 | H33: =MONTH(Registros[[#This Row],[Fecha]]) -> 3 | I33: =YEAR(Registros[[#This Row],[Fecha]]) -> 2026 | J33: =OR(ISNUMBER(FIND("Sueldo",Registros[[#This Row],[Descripción]])),ISNUMBER(FIND("sueldo",Registros[[#This Row],[Descripción]]))) -> FALSE | K33: =OR(ISNUMBER(FIND("Javi",Registros[[#This Row],[Descripción]])),ISNUMBER(FIND("javi",Registros[[#This Row],[Descripción]]))) -> FALSE
B34: 46089 | C34: Sansivierias | D34: Deseos | E34: Compras dpto | G34: 25000 | H34: =MONTH(Registros[[#This Row],[Fecha]]) -> 3 | I34: =YEAR(Registros[[#This Row],[Fecha]]) -> 2026 | J34: =OR(ISNUMBER(FIND("Sueldo",Registros[[#This Row],[Descripción]])),ISNUMBER(FIND("sueldo",Registros[[#This Row],[Descripción]]))) -> FALSE | K34: =OR(ISNUMBER(FIND("Javi",Registros[[#This Row],[Descripción]])),ISNUMBER(FIND("javi",Registros[[#This Row],[Descripción]]))) -> FALSE
B35: 46089 | C35: Compra unimarc | D35: Gastos del mes | E35: Supermercado | G35: 15030 | H35: =MONTH(Registros[[#This Row],[Fecha]]) -> 3 | I35: =YEAR(Registros[[#This Row],[Fecha]]) -> 2026 | J35: =OR(ISNUMBER(FIND("Sueldo",Registros[[#This Row],[Descripción]])),ISNUMBER(FIND("sueldo",Registros[[#This Row],[Descripción]]))) -> FALSE | K35: =OR(ISNUMBER(FIND("Javi",Registros[[#This Row],[Descripción]])),ISNUMBER(FIND("javi",Registros[[#This Row],[Descripción]]))) -> FALSE
B36: 46089 | C36: Terno matrimonio | D36: Deseos | E36: Ropa | G36: 74996 | H36: =MONTH(Registros[[#This Row],[Fecha]]) -> 3 | I36: =YEAR(Registros[[#This Row],[Fecha]]) -> 2026 | J36: =OR(ISNUMBER(FIND("Sueldo",Registros[[#This Row],[Descripción]])),ISNUMBER(FIND("sueldo",Registros[[#This Row],[Descripción]]))) -> FALSE | K36: =OR(ISNUMBER(FIND("Javi",Registros[[#This Row],[Descripción]])),ISNUMBER(FIND("javi",Registros[[#This Row],[Descripción]]))) -> FALSE
B37: 46089 | C37: Ropa matrimonio | D37: Deseos | E37: Ropa | G37: 53980 | H37: =MONTH(Registros[[#This Row],[Fecha]]) -> 3 | I37: =YEAR(Registros[[#This Row],[Fecha]]) -> 2026 | J37: =OR(ISNUMBER(FIND("Sueldo",Registros[[#This Row],[Descripción]])),ISNUMBER(FIND("sueldo",Registros[[#This Row],[Descripción]]))) -> FALSE | K37: =OR(ISNUMBER(FIND("Javi",Registros[[#This Row],[Descripción]])),ISNUMBER(FIND("javi",Registros[[#This Row],[Descripción]]))) -> FALSE
B38: 46089 | C38: Ripley | D38: Deseos | E38: Ropa | G38: 24990 | H38: =MONTH(Registros[[#This Row],[Fecha]]) -> 3 | I38: =YEAR(Registros[[#This Row],[Fecha]]) -> 2026 | J38: =OR(ISNUMBER(FIND("Sueldo",Registros[[#This Row],[Descripción]])),ISNUMBER(FIND("sueldo",Registros[[#This Row],[Descripción]]))) -> FALSE | K38: =OR(ISNUMBER(FIND("Javi",Registros[[#This Row],[Descripción]])),ISNUMBER(FIND("javi",Registros[[#This Row],[Descripción]]))) -> FALSE
B39: 46089 | C39: M Plaza egaña | D39: Deseos | E39: Regalos | G39: 28875 | H39: =MONTH(Registros[[#This Row],[Fecha]]) -> 3 | I39: =YEAR(Registros[[#This Row],[Fecha]]) -> 2026 | J39: =OR(ISNUMBER(FIND("Sueldo",Registros[[#This Row],[Descripción]])),ISNUMBER(FIND("sueldo",Registros[[#This Row],[Descripción]]))) -> FALSE | K39: =OR(ISNUMBER(FIND("Javi",Registros[[#This Row],[Descripción]])),ISNUMBER(FIND("javi",Registros[[#This Row],[Descripción]]))) -> FALSE
B40: 46089 | D40: Deseos | E40: Salida a comer | G40: 7100 | H40: =MONTH(Registros[[#This Row],[Fecha]]) -> 3 | I40: =YEAR(Registros[[#This Row],[Fecha]]) -> 2026 | J40: =OR(ISNUMBER(FIND("Sueldo",Registros[[#This Row],[Descripción]])),ISNUMBER(FIND("sueldo",Registros[[#This Row],[Descripción]]))) -> FALSE | K40: =OR(ISNUMBER(FIND("Javi",Registros[[#This Row],[Descripción]])),ISNUMBER(FIND("javi",Registros[[#This Row],[Descripción]]))) -> FALSE
B41: 46090 | C41: Instalación luces dpto (Clemente) | D41: Deseos | E41: Otros | G41: 15000 | H41: =MONTH(Registros[[#This Row],[Fecha]]) -> 3 | I41: =YEAR(Registros[[#This Row],[Fecha]]) -> 2026 | J41: =OR(ISNUMBER(FIND("Sueldo",Registros[[#This Row],[Descripción]])),ISNUMBER(FIND("sueldo",Registros[[#This Row],[Descripción]]))) -> FALSE | K41: =OR(ISNUMBER(FIND("Javi",Registros[[#This Row],[Descripción]])),ISNUMBER(FIND("javi",Registros[[#This Row],[Descripción]]))) -> FALSE
B42: 46090 | C42: Ampolletas auto | D42: Deseos | E42: Auto | G42: 10500 | H42: =MONTH(Registros[[#This Row],[Fecha]]) -> 3 | I42: =YEAR(Registros[[#This Row],[Fecha]]) -> 2026 | J42: =OR(ISNUMBER(FIND("Sueldo",Registros[[#This Row],[Descripción]])),ISNUMBER(FIND("sueldo",Registros[[#This Row],[Descripción]]))) -> FALSE | K42: =OR(ISNUMBER(FIND("Javi",Registros[[#This Row],[Descripción]])),ISNUMBER(FIND("javi",Registros[[#This Row],[Descripción]]))) -> FALSE
B43: 46091 | C43: Compra unimarc | D43: Gastos del mes | E43: Supermercado | G43: 64046 | H43: =MONTH(Registros[[#This Row],[Fecha]]) -> 3 | I43: =YEAR(Registros[[#This Row],[Fecha]]) -> 2026 | J43: =OR(ISNUMBER(FIND("Sueldo",Registros[[#This Row],[Descripción]])),ISNUMBER(FIND("sueldo",Registros[[#This Row],[Descripción]]))) -> FALSE | K43: =OR(ISNUMBER(FIND("Javi",Registros[[#This Row],[Descripción]])),ISNUMBER(FIND("javi",Registros[[#This Row],[Descripción]]))) -> FALSE
B44: 46091 | C44: Compra unimarc | D44: Gastos del mes | E44: Supermercado | G44: 42236 | H44: =MONTH(Registros[[#This Row],[Fecha]]) -> 3 | I44: =YEAR(Registros[[#This Row],[Fecha]]) -> 2026 | J44: =OR(ISNUMBER(FIND("Sueldo",Registros[[#This Row],[Descripción]])),ISNUMBER(FIND("sueldo",Registros[[#This Row],[Descripción]]))) -> FALSE | K44: =OR(ISNUMBER(FIND("Javi",Registros[[#This Row],[Descripción]])),ISNUMBER(FIND("javi",Registros[[#This Row],[Descripción]]))) -> FALSE
B45: 46091 | D45: Deseos | G45: 2400 | H45: =MONTH(Registros[[#This Row],[Fecha]]) -> 3 | I45: =YEAR(Registros[[#This Row],[Fecha]]) -> 2026 | J45: =OR(ISNUMBER(FIND("Sueldo",Registros[[#This Row],[Descripción]])),ISNUMBER(FIND("sueldo",Registros[[#This Row],[Descripción]]))) -> FALSE | K45: =OR(ISNUMBER(FIND("Javi",Registros[[#This Row],[Descripción]])),ISNUMBER(FIND("javi",Registros[[#This Row],[Descripción]]))) -> FALSE
B46: 46091 | D46: Deseos | G46: 7800 | H46: =MONTH(Registros[[#This Row],[Fecha]]) -> 3 | I46: =YEAR(Registros[[#This Row],[Fecha]]) -> 2026 | J46: =OR(ISNUMBER(FIND("Sueldo",Registros[[#This Row],[Descripción]])),ISNUMBER(FIND("sueldo",Registros[[#This Row],[Descripción]]))) -> FALSE | K46: =OR(ISNUMBER(FIND("Javi",Registros[[#This Row],[Descripción]])),ISNUMBER(FIND("javi",Registros[[#This Row],[Descripción]]))) -> FALSE
B47: 46091 | D47: Deseos | G47: 5000 | H47: =MONTH(Registros[[#This Row],[Fecha]]) -> 3 | I47: =YEAR(Registros[[#This Row],[Fecha]]) -> 2026 | J47: =OR(ISNUMBER(FIND("Sueldo",Registros[[#This Row],[Descripción]])),ISNUMBER(FIND("sueldo",Registros[[#This Row],[Descripción]]))) -> FALSE | K47: =OR(ISNUMBER(FIND("Javi",Registros[[#This Row],[Descripción]])),ISNUMBER(FIND("javi",Registros[[#This Row],[Descripción]]))) -> FALSE
B48: 46091 | D48: Deseos | G48: 18980 | H48: =MONTH(Registros[[#This Row],[Fecha]]) -> 3 | I48: =YEAR(Registros[[#This Row],[Fecha]]) -> 2026 | J48: =OR(ISNUMBER(FIND("Sueldo",Registros[[#This Row],[Descripción]])),ISNUMBER(FIND("sueldo",Registros[[#This Row],[Descripción]]))) -> FALSE | K48: =OR(ISNUMBER(FIND("Javi",Registros[[#This Row],[Descripción]])),ISNUMBER(FIND("javi",Registros[[#This Row],[Descripción]]))) -> FALSE
B49: 46092 | C49: Carga Bip! | D49: Gastos del mes | E49: Transporte | G49: 10000 | H49: =MONTH(Registros[[#This Row],[Fecha]]) -> 3 | I49: =YEAR(Registros[[#This Row],[Fecha]]) -> 2026 | J49: =OR(ISNUMBER(FIND("Sueldo",Registros[[#This Row],[Descripción]])),ISNUMBER(FIND("sueldo",Registros[[#This Row],[Descripción]]))) -> FALSE | K49: =OR(ISNUMBER(FIND("Javi",Registros[[#This Row],[Descripción]])),ISNUMBER(FIND("javi",Registros[[#This Row],[Descripción]]))) -> FALSE
B50: 46092 | C50: Compra unimarc | D50: Gastos del mes | E50: Supermercado | G50: 20999 | H50: =MONTH(Registros[[#This Row],[Fecha]]) -> 3 | I50: =YEAR(Registros[[#This Row],[Fecha]]) -> 2026 | J50: =OR(ISNUMBER(FIND("Sueldo",Registros[[#This Row],[Descripción]])),ISNUMBER(FIND("sueldo",Registros[[#This Row],[Descripción]]))) -> FALSE | K50: =OR(ISNUMBER(FIND("Javi",Registros[[#This Row],[Descripción]])),ISNUMBER(FIND("javi",Registros[[#This Row],[Descripción]]))) -> FALSE
B51: 46094 | D51: Deseos | G51: 10100 | H51: =MONTH(Registros[[#This Row],[Fecha]]) -> 3 | I51: =YEAR(Registros[[#This Row],[Fecha]]) -> 2026 | J51: =OR(ISNUMBER(FIND("Sueldo",Registros[[#This Row],[Descripción]])),ISNUMBER(FIND("sueldo",Registros[[#This Row],[Descripción]]))) -> FALSE | K51: =OR(ISNUMBER(FIND("Javi",Registros[[#This Row],[Descripción]])),ISNUMBER(FIND("javi",Registros[[#This Row],[Descripción]]))) -> FALSE
B52: 46095 | C52: Carga bencina (Inicio vacaciones) | D52: Deseos | E52: Auto | G52: 19593 | H52: =MONTH(Registros[[#This Row],[Fecha]]) -> 3 | I52: =YEAR(Registros[[#This Row],[Fecha]]) -> 2026 | J52: =OR(ISNUMBER(FIND("Sueldo",Registros[[#This Row],[Descripción]])),ISNUMBER(FIND("sueldo",Registros[[#This Row],[Descripción]]))) -> FALSE | K52: =OR(ISNUMBER(FIND("Javi",Registros[[#This Row],[Descripción]])),ISNUMBER(FIND("javi",Registros[[#This Row],[Descripción]]))) -> FALSE
B53: 46095 | C53: Giro efectivo | D53: Deseos | G53: 50000 | H53: =MONTH(Registros[[#This Row],[Fecha]]) -> 3 | I53: =YEAR(Registros[[#This Row],[Fecha]]) -> 2026 | J53: =OR(ISNUMBER(FIND("Sueldo",Registros[[#This Row],[Descripción]])),ISNUMBER(FIND("sueldo",Registros[[#This Row],[Descripción]]))) -> FALSE | K53: =OR(ISNUMBER(FIND("Javi",Registros[[#This Row],[Descripción]])),ISNUMBER(FIND("javi",Registros[[#This Row],[Descripción]]))) -> FALSE
B54: 46095 | C54: Bencina | D54: Deseos | E54: Auto | G54: 60000 | H54: =MONTH(Registros[[#This Row],[Fecha]]) -> 3 | I54: =YEAR(Registros[[#This Row],[Fecha]]) -> 2026 | J54: =OR(ISNUMBER(FIND("Sueldo",Registros[[#This Row],[Descripción]])),ISNUMBER(FIND("sueldo",Registros[[#This Row],[Descripción]]))) -> FALSE | K54: =OR(ISNUMBER(FIND("Javi",Registros[[#This Row],[Descripción]])),ISNUMBER(FIND("javi",Registros[[#This Row],[Descripción]]))) -> FALSE
B55: 46095 | C55: Cabaña Bahia Coique (Cofa) | D55: Deseos | E55: Otros | F55: 20000 | H55: =MONTH(Registros[[#This Row],[Fecha]]) -> 3 | I55: =YEAR(Registros[[#This Row],[Fecha]]) -> 2026 | J55: =OR(ISNUMBER(FIND("Sueldo",Registros[[#This Row],[Descripción]])),ISNUMBER(FIND("sueldo",Registros[[#This Row],[Descripción]]))) -> FALSE | K55: =OR(ISNUMBER(FIND("Javi",Registros[[#This Row],[Descripción]])),ISNUMBER(FIND("javi",Registros[[#This Row],[Descripción]]))) -> FALSE
B56: 46095 | C56: Bencina | D56: Deseos | E56: Auto | G56: 30925 | H56: =MONTH(Registros[[#This Row],[Fecha]]) -> 3 | I56: =YEAR(Registros[[#This Row],[Fecha]]) -> 2026 | J56: =OR(ISNUMBER(FIND("Sueldo",Registros[[#This Row],[Descripción]])),ISNUMBER(FIND("sueldo",Registros[[#This Row],[Descripción]]))) -> FALSE | K56: =OR(ISNUMBER(FIND("Javi",Registros[[#This Row],[Descripción]])),ISNUMBER(FIND("javi",Registros[[#This Row],[Descripción]]))) -> FALSE
B57: 46095 | C57: Cabaña Bahia Coique | D57: Deseos | E57: Otros | G57: 99600 | H57: =MONTH(Registros[[#This Row],[Fecha]]) -> 3 | I57: =YEAR(Registros[[#This Row],[Fecha]]) -> 2026 | J57: =OR(ISNUMBER(FIND("Sueldo",Registros[[#This Row],[Descripción]])),ISNUMBER(FIND("sueldo",Registros[[#This Row],[Descripción]]))) -> FALSE | K57: =OR(ISNUMBER(FIND("Javi",Registros[[#This Row],[Descripción]])),ISNUMBER(FIND("javi",Registros[[#This Row],[Descripción]]))) -> FALSE
B58: 46096 | C58: Compra comida cabaña Futangue | D58: Deseos | E58: Otros | G58: 50780 | H58: =MONTH(Registros[[#This Row],[Fecha]]) -> 3 | I58: =YEAR(Registros[[#This Row],[Fecha]]) -> 2026 | J58: =OR(ISNUMBER(FIND("Sueldo",Registros[[#This Row],[Descripción]])),ISNUMBER(FIND("sueldo",Registros[[#This Row],[Descripción]]))) -> FALSE | K58: =OR(ISNUMBER(FIND("Javi",Registros[[#This Row],[Descripción]])),ISNUMBER(FIND("javi",Registros[[#This Row],[Descripción]]))) -> FALSE
B59: 46097 | C59: Cafeteria parque futangue | D59: Deseos | E59: Salida a comer | G59: 20020 | H59: =MONTH(Registros[[#This Row],[Fecha]]) -> 3 | I59: =YEAR(Registros[[#This Row],[Fecha]]) -> 2026 | J59: =OR(ISNUMBER(FIND("Sueldo",Registros[[#This Row],[Descripción]])),ISNUMBER(FIND("sueldo",Registros[[#This Row],[Descripción]]))) -> FALSE | K59: =OR(ISNUMBER(FIND("Javi",Registros[[#This Row],[Descripción]])),ISNUMBER(FIND("javi",Registros[[#This Row],[Descripción]]))) -> FALSE
B60: 46098 | C60: Cabaña Bahia Coique (Joaco) + Bencina | D60: Deseos | E60: Otros | F60: 29920 | H60: =MONTH(Registros[[#This Row],[Fecha]]) -> 3 | I60: =YEAR(Registros[[#This Row],[Fecha]]) -> 2026 | J60: =OR(ISNUMBER(FIND("Sueldo",Registros[[#This Row],[Descripción]])),ISNUMBER(FIND("sueldo",Registros[[#This Row],[Descripción]]))) -> FALSE | K60: =OR(ISNUMBER(FIND("Javi",Registros[[#This Row],[Descripción]])),ISNUMBER(FIND("javi",Registros[[#This Row],[Descripción]]))) -> FALSE
B61: 46098 | C61: Termas cancagua | D61: Deseos | E61: Otros | G61: 72000 | H61: =MONTH(Registros[[#This Row],[Fecha]]) -> 3 | I61: =YEAR(Registros[[#This Row],[Fecha]]) -> 2026 | J61: =OR(ISNUMBER(FIND("Sueldo",Registros[[#This Row],[Descripción]])),ISNUMBER(FIND("sueldo",Registros[[#This Row],[Descripción]]))) -> FALSE | K61: =OR(ISNUMBER(FIND("Javi",Registros[[#This Row],[Descripción]])),ISNUMBER(FIND("javi",Registros[[#This Row],[Descripción]]))) -> FALSE
B62: 46098 | C62: Regalo Matri Oyane & Isi | D62: Deseos | E62: Regalos | G62: 100000 | H62: =MONTH(Registros[[#This Row],[Fecha]]) -> 3 | I62: =YEAR(Registros[[#This Row],[Fecha]]) -> 2026 | J62: =OR(ISNUMBER(FIND("Sueldo",Registros[[#This Row],[Descripción]])),ISNUMBER(FIND("sueldo",Registros[[#This Row],[Descripción]]))) -> FALSE | K62: =OR(ISNUMBER(FIND("Javi",Registros[[#This Row],[Descripción]])),ISNUMBER(FIND("javi",Registros[[#This Row],[Descripción]]))) -> FALSE
B63: 46098 | C63: Cafeteria cancagua | D63: Deseos | E63: Salida a comer | G63: 19250 | H63: =MONTH(Registros[[#This Row],[Fecha]]) -> 3 | I63: =YEAR(Registros[[#This Row],[Fecha]]) -> 2026 | J63: =OR(ISNUMBER(FIND("Sueldo",Registros[[#This Row],[Descripción]])),ISNUMBER(FIND("sueldo",Registros[[#This Row],[Descripción]]))) -> FALSE | K63: =OR(ISNUMBER(FIND("Javi",Registros[[#This Row],[Descripción]])),ISNUMBER(FIND("javi",Registros[[#This Row],[Descripción]]))) -> FALSE
B64: 46099 | C64: Cena club alemán Frutillar | D64: Deseos | E64: Salida a comer | G64: 72325 | H64: =MONTH(Registros[[#This Row],[Fecha]]) -> 3 | I64: =YEAR(Registros[[#This Row],[Fecha]]) -> 2026 | J64: =OR(ISNUMBER(FIND("Sueldo",Registros[[#This Row],[Descripción]])),ISNUMBER(FIND("sueldo",Registros[[#This Row],[Descripción]]))) -> FALSE | K64: =OR(ISNUMBER(FIND("Javi",Registros[[#This Row],[Descripción]])),ISNUMBER(FIND("javi",Registros[[#This Row],[Descripción]]))) -> FALSE
B65: 46100 | C65: Despedida soltero Oyane (Joaco) | D65: Deseos | E65: Carrete | F65: 164834 | H65: =MONTH(Registros[[#This Row],[Fecha]]) -> 3 | I65: =YEAR(Registros[[#This Row],[Fecha]]) -> 2026 | J65: =OR(ISNUMBER(FIND("Sueldo",Registros[[#This Row],[Descripción]])),ISNUMBER(FIND("sueldo",Registros[[#This Row],[Descripción]]))) -> FALSE | K65: =OR(ISNUMBER(FIND("Javi",Registros[[#This Row],[Descripción]])),ISNUMBER(FIND("javi",Registros[[#This Row],[Descripción]]))) -> FALSE
B66: 46100 | D66: Deseos | G66: 1107 | H66: =MONTH(Registros[[#This Row],[Fecha]]) -> 3 | I66: =YEAR(Registros[[#This Row],[Fecha]]) -> 2026 | J66: =OR(ISNUMBER(FIND("Sueldo",Registros[[#This Row],[Descripción]])),ISNUMBER(FIND("sueldo",Registros[[#This Row],[Descripción]]))) -> FALSE | K66: =OR(ISNUMBER(FIND("Javi",Registros[[#This Row],[Descripción]])),ISNUMBER(FIND("javi",Registros[[#This Row],[Descripción]]))) -> FALSE
B67: 46100 | C67: Compra supermercado frutillar | D67: Gastos del mes | E67: Supermercado | G67: 6900 | H67: =MONTH(Registros[[#This Row],[Fecha]]) -> 3 | I67: =YEAR(Registros[[#This Row],[Fecha]]) -> 2026 | J67: =OR(ISNUMBER(FIND("Sueldo",Registros[[#This Row],[Descripción]])),ISNUMBER(FIND("sueldo",Registros[[#This Row],[Descripción]]))) -> FALSE | K67: =OR(ISNUMBER(FIND("Javi",Registros[[#This Row],[Descripción]])),ISNUMBER(FIND("javi",Registros[[#This Row],[Descripción]]))) -> FALSE
B68: 46101 | C68: Almuerzo angelmó | D68: Deseos | E68: Salida a comer | G68: 35000 | H68: =MONTH(Registros[[#This Row],[Fecha]]) -> 3 | I68: =YEAR(Registros[[#This Row],[Fecha]]) -> 2026 | J68: =OR(ISNUMBER(FIND("Sueldo",Registros[[#This Row],[Descripción]])),ISNUMBER(FIND("sueldo",Registros[[#This Row],[Descripción]]))) -> FALSE | K68: =OR(ISNUMBER(FIND("Javi",Registros[[#This Row],[Descripción]])),ISNUMBER(FIND("javi",Registros[[#This Row],[Descripción]]))) -> FALSE
B69: 46102 | C69: Ilustraciones aves Frutillar | D69: Deseos | E69: Compras dpto | G69: 23000 | H69: =MONTH(Registros[[#This Row],[Fecha]]) -> 3 | I69: =YEAR(Registros[[#This Row],[Fecha]]) -> 2026 | J69: =OR(ISNUMBER(FIND("Sueldo",Registros[[#This Row],[Descripción]])),ISNUMBER(FIND("sueldo",Registros[[#This Row],[Descripción]]))) -> FALSE | K69: =OR(ISNUMBER(FIND("Javi",Registros[[#This Row],[Descripción]])),ISNUMBER(FIND("javi",Registros[[#This Row],[Descripción]]))) -> FALSE
B70: 46102 | C70: Kuchen | D70: Deseos | G70: 15600 | H70: =MONTH(Registros[[#This Row],[Fecha]]) -> 3 | I70: =YEAR(Registros[[#This Row],[Fecha]]) -> 2026 | J70: =OR(ISNUMBER(FIND("Sueldo",Registros[[#This Row],[Descripción]])),ISNUMBER(FIND("sueldo",Registros[[#This Row],[Descripción]]))) -> FALSE | K70: =OR(ISNUMBER(FIND("Javi",Registros[[#This Row],[Descripción]])),ISNUMBER(FIND("javi",Registros[[#This Row],[Descripción]]))) -> FALSE
B71: 46103 | C71: Bencina | D71: Deseos | E71: Auto | G71: 60000 | H71: =MONTH(Registros[[#This Row],[Fecha]]) -> 3 | I71: =YEAR(Registros[[#This Row],[Fecha]]) -> 2026 | J71: =OR(ISNUMBER(FIND("Sueldo",Registros[[#This Row],[Descripción]])),ISNUMBER(FIND("sueldo",Registros[[#This Row],[Descripción]]))) -> FALSE | K71: =OR(ISNUMBER(FIND("Javi",Registros[[#This Row],[Descripción]])),ISNUMBER(FIND("javi",Registros[[#This Row],[Descripción]]))) -> FALSE | N71: =SUM(G52:G72)-G57 -> 651500
B72: 46103 | C72: Bencina (Fin vacaciones) | D72: Deseos | E72: Auto | G72: 15000 | H72: =MONTH(Registros[[#This Row],[Fecha]]) -> 3 | I72: =YEAR(Registros[[#This Row],[Fecha]]) -> 2026 | J72: =OR(ISNUMBER(FIND("Sueldo",Registros[[#This Row],[Descripción]])),ISNUMBER(FIND("sueldo",Registros[[#This Row],[Descripción]]))) -> FALSE | K72: =OR(ISNUMBER(FIND("Javi",Registros[[#This Row],[Descripción]])),ISNUMBER(FIND("javi",Registros[[#This Row],[Descripción]]))) -> FALSE
B73: 46104 | C73: GGCC mes Febrero | D73: Gastos del mes | E73: Cuentas | G73: 117369 | H73: =MONTH(Registros[[#This Row],[Fecha]]) -> 3 | I73: =YEAR(Registros[[#This Row],[Fecha]]) -> 2026 | J73: =OR(ISNUMBER(FIND("Sueldo",Registros[[#This Row],[Descripción]])),ISNUMBER(FIND("sueldo",Registros[[#This Row],[Descripción]]))) -> FALSE | K73: =OR(ISNUMBER(FIND("Javi",Registros[[#This Row],[Descripción]])),ISNUMBER(FIND("javi",Registros[[#This Row],[Descripción]]))) -> FALSE
B74: 46106 | C74: Carga Bip | D74: Gastos del mes | E74: Transporte | G74: 10000 | H74: =MONTH(Registros[[#This Row],[Fecha]]) -> 3 | I74: =YEAR(Registros[[#This Row],[Fecha]]) -> 2026 | J74: =OR(ISNUMBER(FIND("Sueldo",Registros[[#This Row],[Descripción]])),ISNUMBER(FIND("sueldo",Registros[[#This Row],[Descripción]]))) -> FALSE | K74: =OR(ISNUMBER(FIND("Javi",Registros[[#This Row],[Descripción]])),ISNUMBER(FIND("javi",Registros[[#This Row],[Descripción]]))) -> FALSE
B75: 46107 | C75: Autorescate plata desde cta ahorro | D75: Deseos | E75: Cuenta Ahorro | F75: 60000 | H75: =MONTH(Registros[[#This Row],[Fecha]]) -> 3 | I75: =YEAR(Registros[[#This Row],[Fecha]]) -> 2026 | J75: =OR(ISNUMBER(FIND("Sueldo",Registros[[#This Row],[Descripción]])),ISNUMBER(FIND("sueldo",Registros[[#This Row],[Descripción]]))) -> FALSE | K75: =OR(ISNUMBER(FIND("Javi",Registros[[#This Row],[Descripción]])),ISNUMBER(FIND("javi",Registros[[#This Row],[Descripción]]))) -> FALSE
B76: 46107 | C76: Compra maceteros | D76: Deseos | E76: Compras dpto | G76: 49450 | H76: =MONTH(Registros[[#This Row],[Fecha]]) -> 3 | I76: =YEAR(Registros[[#This Row],[Fecha]]) -> 2026 | J76: =OR(ISNUMBER(FIND("Sueldo",Registros[[#This Row],[Descripción]])),ISNUMBER(FIND("sueldo",Registros[[#This Row],[Descripción]]))) -> FALSE | K76: =OR(ISNUMBER(FIND("Javi",Registros[[#This Row],[Descripción]])),ISNUMBER(FIND("javi",Registros[[#This Row],[Descripción]]))) -> FALSE
B77: 46107 | C77: Estacionamiento Portal ñuñoa | D77: Deseos | E77: Auto | G77: 350 | H77: =MONTH(Registros[[#This Row],[Fecha]]) -> 3 | I77: =YEAR(Registros[[#This Row],[Fecha]]) -> 2026 | J77: =OR(ISNUMBER(FIND("Sueldo",Registros[[#This Row],[Descripción]])),ISNUMBER(FIND("sueldo",Registros[[#This Row],[Descripción]]))) -> FALSE | K77: =OR(ISNUMBER(FIND("Javi",Registros[[#This Row],[Descripción]])),ISNUMBER(FIND("javi",Registros[[#This Row],[Descripción]]))) -> FALSE
B78: 46108 | C78: Compra unimarc | D78: Gastos del mes | E78: Supermercado | G78: 11680 | H78: =MONTH(Registros[[#This Row],[Fecha]]) -> 3 | I78: =YEAR(Registros[[#This Row],[Fecha]]) -> 2026 | J78: =OR(ISNUMBER(FIND("Sueldo",Registros[[#This Row],[Descripción]])),ISNUMBER(FIND("sueldo",Registros[[#This Row],[Descripción]]))) -> FALSE | K78: =OR(ISNUMBER(FIND("Javi",Registros[[#This Row],[Descripción]])),ISNUMBER(FIND("javi",Registros[[#This Row],[Descripción]]))) -> FALSE
B79: 46113 | C79: Sueldo abril | D79: Gastos del mes | F79: 1795336 | H79: =MONTH(Registros[[#This Row],[Fecha]]) -> 4 | I79: =YEAR(Registros[[#This Row],[Fecha]]) -> 2026 | J79: =OR(ISNUMBER(FIND("Sueldo",Registros[[#This Row],[Descripción]])),ISNUMBER(FIND("sueldo",Registros[[#This Row],[Descripción]]))) -> TRUE | K79: =OR(ISNUMBER(FIND("Javi",Registros[[#This Row],[Descripción]])),ISNUMBER(FIND("javi",Registros[[#This Row],[Descripción]]))) -> FALSE
B80: 46113 | D80: Deseos | G80: 5000 | H80: =MONTH(Registros[[#This Row],[Fecha]]) -> 4 | I80: =YEAR(Registros[[#This Row],[Fecha]]) -> 2026 | J80: =OR(ISNUMBER(FIND("Sueldo",Registros[[#This Row],[Descripción]])),ISNUMBER(FIND("sueldo",Registros[[#This Row],[Descripción]]))) -> FALSE | K80: =OR(ISNUMBER(FIND("Javi",Registros[[#This Row],[Descripción]])),ISNUMBER(FIND("javi",Registros[[#This Row],[Descripción]]))) -> FALSE
B81: 46113 | C81: Huevitos de chocolate | D81: Deseos | E81: Regalos | G81: 30000 | H81: =MONTH(Registros[[#This Row],[Fecha]]) -> 4 | I81: =YEAR(Registros[[#This Row],[Fecha]]) -> 2026 | J81: =OR(ISNUMBER(FIND("Sueldo",Registros[[#This Row],[Descripción]])),ISNUMBER(FIND("sueldo",Registros[[#This Row],[Descripción]]))) -> FALSE | K81: =OR(ISNUMBER(FIND("Javi",Registros[[#This Row],[Descripción]])),ISNUMBER(FIND("javi",Registros[[#This Row],[Descripción]]))) -> FALSE
B82: 46113 | C82: Completos dominó Pool(Kako) | D82: Deseos | E82: Salida a comer | F82: 15533 | H82: =MONTH(Registros[[#This Row],[Fecha]]) -> 4 | I82: =YEAR(Registros[[#This Row],[Fecha]]) -> 2026 | J82: =OR(ISNUMBER(FIND("Sueldo",Registros[[#This Row],[Descripción]])),ISNUMBER(FIND("sueldo",Registros[[#This Row],[Descripción]]))) -> FALSE | K82: =OR(ISNUMBER(FIND("Javi",Registros[[#This Row],[Descripción]])),ISNUMBER(FIND("javi",Registros[[#This Row],[Descripción]]))) -> FALSE
B83: 46113 | C83: Compra farmarcia | D83: Gastos del mes | E83: Salud | G83: 36033 | H83: =MONTH(Registros[[#This Row],[Fecha]]) -> 4 | I83: =YEAR(Registros[[#This Row],[Fecha]]) -> 2026 | J83: =OR(ISNUMBER(FIND("Sueldo",Registros[[#This Row],[Descripción]])),ISNUMBER(FIND("sueldo",Registros[[#This Row],[Descripción]]))) -> FALSE | K83: =OR(ISNUMBER(FIND("Javi",Registros[[#This Row],[Descripción]])),ISNUMBER(FIND("javi",Registros[[#This Row],[Descripción]]))) -> FALSE
B84: 46113 | C84: Compra muebles y decoración IKEA | D84: Deseos | E84: Compras dpto | G84: 343340 | H84: =MONTH(Registros[[#This Row],[Fecha]]) -> 4 | I84: =YEAR(Registros[[#This Row],[Fecha]]) -> 2026 | J84: =OR(ISNUMBER(FIND("Sueldo",Registros[[#This Row],[Descripción]])),ISNUMBER(FIND("sueldo",Registros[[#This Row],[Descripción]]))) -> FALSE | K84: =OR(ISNUMBER(FIND("Javi",Registros[[#This Row],[Descripción]])),ISNUMBER(FIND("javi",Registros[[#This Row],[Descripción]]))) -> FALSE
B85: 46113 | C85: Arriendo y cuentas Javi | D85: Gastos del mes | E85: Arriendo | F85: 360000 | H85: =MONTH(Registros[[#This Row],[Fecha]]) -> 4 | I85: =YEAR(Registros[[#This Row],[Fecha]]) -> 2026 | J85: =OR(ISNUMBER(FIND("Sueldo",Registros[[#This Row],[Descripción]])),ISNUMBER(FIND("sueldo",Registros[[#This Row],[Descripción]]))) -> FALSE | K85: =OR(ISNUMBER(FIND("Javi",Registros[[#This Row],[Descripción]])),ISNUMBER(FIND("javi",Registros[[#This Row],[Descripción]]))) -> TRUE
B86: 46113 | C86: Cuenta aguas andinas (febrero y marzo) | D86: Gastos del mes | E86: Cuentas | G86: 32080 | H86: =MONTH(Registros[[#This Row],[Fecha]]) -> 4 | I86: =YEAR(Registros[[#This Row],[Fecha]]) -> 2026 | J86: =OR(ISNUMBER(FIND("Sueldo",Registros[[#This Row],[Descripción]])),ISNUMBER(FIND("sueldo",Registros[[#This Row],[Descripción]]))) -> FALSE | K86: =OR(ISNUMBER(FIND("Javi",Registros[[#This Row],[Descripción]])),ISNUMBER(FIND("javi",Registros[[#This Row],[Descripción]]))) -> FALSE
B87: 46113 | C87: Cuenta movistar | D87: Gastos del mes | E87: Cuentas | G87: 13360 | H87: =MONTH(Registros[[#This Row],[Fecha]]) -> 4 | I87: =YEAR(Registros[[#This Row],[Fecha]]) -> 2026 | J87: =OR(ISNUMBER(FIND("Sueldo",Registros[[#This Row],[Descripción]])),ISNUMBER(FIND("sueldo",Registros[[#This Row],[Descripción]]))) -> FALSE | K87: =OR(ISNUMBER(FIND("Javi",Registros[[#This Row],[Descripción]])),ISNUMBER(FIND("javi",Registros[[#This Row],[Descripción]]))) -> FALSE
B88: 46113 | C88: Metrogas | D88: Gastos del mes | E88: Cuentas | G88: 66105 | H88: =MONTH(Registros[[#This Row],[Fecha]]) -> 4 | I88: =YEAR(Registros[[#This Row],[Fecha]]) -> 2026 | J88: =OR(ISNUMBER(FIND("Sueldo",Registros[[#This Row],[Descripción]])),ISNUMBER(FIND("sueldo",Registros[[#This Row],[Descripción]]))) -> FALSE | K88: =OR(ISNUMBER(FIND("Javi",Registros[[#This Row],[Descripción]])),ISNUMBER(FIND("javi",Registros[[#This Row],[Descripción]]))) -> FALSE
B89: 46113 | C89: Enel | D89: Gastos del mes | E89: Cuentas | G89: 30598 | H89: =MONTH(Registros[[#This Row],[Fecha]]) -> 4 | I89: =YEAR(Registros[[#This Row],[Fecha]]) -> 2026 | J89: =OR(ISNUMBER(FIND("Sueldo",Registros[[#This Row],[Descripción]])),ISNUMBER(FIND("sueldo",Registros[[#This Row],[Descripción]]))) -> FALSE | K89: =OR(ISNUMBER(FIND("Javi",Registros[[#This Row],[Descripción]])),ISNUMBER(FIND("javi",Registros[[#This Row],[Descripción]]))) -> FALSE
B90: 46113 | C90: Arriendo abril | D90: Gastos del mes | E90: Arriendo | G90: 700000 | H90: =MONTH(Registros[[#This Row],[Fecha]]) -> 4 | I90: =YEAR(Registros[[#This Row],[Fecha]]) -> 2026 | J90: =OR(ISNUMBER(FIND("Sueldo",Registros[[#This Row],[Descripción]])),ISNUMBER(FIND("sueldo",Registros[[#This Row],[Descripción]]))) -> FALSE | K90: =OR(ISNUMBER(FIND("Javi",Registros[[#This Row],[Descripción]])),ISNUMBER(FIND("javi",Registros[[#This Row],[Descripción]]))) -> FALSE
B91: 46113 | D91: Deseos | G91: 1600 | H91: =MONTH(Registros[[#This Row],[Fecha]]) -> 4 | I91: =YEAR(Registros[[#This Row],[Fecha]]) -> 2026 | J91: =OR(ISNUMBER(FIND("Sueldo",Registros[[#This Row],[Descripción]])),ISNUMBER(FIND("sueldo",Registros[[#This Row],[Descripción]]))) -> FALSE | K91: =OR(ISNUMBER(FIND("Javi",Registros[[#This Row],[Descripción]])),ISNUMBER(FIND("javi",Registros[[#This Row],[Descripción]]))) -> FALSE
B92: 46114 | C92: Virgin mobile | D92: Gastos del mes | E92: Cuentas | G92: 7990 | H92: =MONTH(Registros[[#This Row],[Fecha]]) -> 4 | I92: =YEAR(Registros[[#This Row],[Fecha]]) -> 2026 | J92: =OR(ISNUMBER(FIND("Sueldo",Registros[[#This Row],[Descripción]])),ISNUMBER(FIND("sueldo",Registros[[#This Row],[Descripción]]))) -> FALSE | K92: =OR(ISNUMBER(FIND("Javi",Registros[[#This Row],[Descripción]])),ISNUMBER(FIND("javi",Registros[[#This Row],[Descripción]]))) -> FALSE
B93: 46114 | C93: Vitrificado mesa | D93: Deseos | E93: Compras dpto | G93: 22812 | H93: =MONTH(Registros[[#This Row],[Fecha]]) -> 4 | I93: =YEAR(Registros[[#This Row],[Fecha]]) -> 2026 | J93: =OR(ISNUMBER(FIND("Sueldo",Registros[[#This Row],[Descripción]])),ISNUMBER(FIND("sueldo",Registros[[#This Row],[Descripción]]))) -> FALSE | K93: =OR(ISNUMBER(FIND("Javi",Registros[[#This Row],[Descripción]])),ISNUMBER(FIND("javi",Registros[[#This Row],[Descripción]]))) -> FALSE
B94: 46114 | C94: Bebida | D94: Deseos | E94: Supermercado | G94: 1790 | H94: =MONTH(Registros[[#This Row],[Fecha]]) -> 4 | I94: =YEAR(Registros[[#This Row],[Fecha]]) -> 2026 | J94: =OR(ISNUMBER(FIND("Sueldo",Registros[[#This Row],[Descripción]])),ISNUMBER(FIND("sueldo",Registros[[#This Row],[Descripción]]))) -> FALSE | K94: =OR(ISNUMBER(FIND("Javi",Registros[[#This Row],[Descripción]])),ISNUMBER(FIND("javi",Registros[[#This Row],[Descripción]]))) -> FALSE
B95: 46114 | C95: Carga Bip | D95: Gastos del mes | E95: Transporte | G95: 10000 | H95: =MONTH(Registros[[#This Row],[Fecha]]) -> 4 | I95: =YEAR(Registros[[#This Row],[Fecha]]) -> 2026 | J95: =OR(ISNUMBER(FIND("Sueldo",Registros[[#This Row],[Descripción]])),ISNUMBER(FIND("sueldo",Registros[[#This Row],[Descripción]]))) -> FALSE | K95: =OR(ISNUMBER(FIND("Javi",Registros[[#This Row],[Descripción]])),ISNUMBER(FIND("javi",Registros[[#This Row],[Descripción]]))) -> FALSE
B96: 46115 | C96: Botilleria | D96: Deseos | E96: Carrete | G96: 7800 | H96: =MONTH(Registros[[#This Row],[Fecha]]) -> 4 | I96: =YEAR(Registros[[#This Row],[Fecha]]) -> 2026 | J96: =OR(ISNUMBER(FIND("Sueldo",Registros[[#This Row],[Descripción]])),ISNUMBER(FIND("sueldo",Registros[[#This Row],[Descripción]]))) -> FALSE | K96: =OR(ISNUMBER(FIND("Javi",Registros[[#This Row],[Descripción]])),ISNUMBER(FIND("javi",Registros[[#This Row],[Descripción]]))) -> FALSE
B97: 46116 | D97: Deseos | G97: 20000 | H97: =MONTH(Registros[[#This Row],[Fecha]]) -> 4 | I97: =YEAR(Registros[[#This Row],[Fecha]]) -> 2026 | J97: =OR(ISNUMBER(FIND("Sueldo",Registros[[#This Row],[Descripción]])),ISNUMBER(FIND("sueldo",Registros[[#This Row],[Descripción]]))) -> FALSE | K97: =OR(ISNUMBER(FIND("Javi",Registros[[#This Row],[Descripción]])),ISNUMBER(FIND("javi",Registros[[#This Row],[Descripción]]))) -> FALSE
B98: 46116 | D98: Deseos | G98: 18469 | H98: =MONTH(Registros[[#This Row],[Fecha]]) -> 4 | I98: =YEAR(Registros[[#This Row],[Fecha]]) -> 2026 | J98: =OR(ISNUMBER(FIND("Sueldo",Registros[[#This Row],[Descripción]])),ISNUMBER(FIND("sueldo",Registros[[#This Row],[Descripción]]))) -> FALSE | K98: =OR(ISNUMBER(FIND("Javi",Registros[[#This Row],[Descripción]])),ISNUMBER(FIND("javi",Registros[[#This Row],[Descripción]]))) -> FALSE
B99: 46116 | C99: Compra lider | D99: Gastos del mes | E99: Supermercado | G99: 7240 | H99: =MONTH(Registros[[#This Row],[Fecha]]) -> 4 | I99: =YEAR(Registros[[#This Row],[Fecha]]) -> 2026 | J99: =OR(ISNUMBER(FIND("Sueldo",Registros[[#This Row],[Descripción]])),ISNUMBER(FIND("sueldo",Registros[[#This Row],[Descripción]]))) -> FALSE | K99: =OR(ISNUMBER(FIND("Javi",Registros[[#This Row],[Descripción]])),ISNUMBER(FIND("javi",Registros[[#This Row],[Descripción]]))) -> FALSE
B100: 46116 | C100: Compra unimarc | D100: Gastos del mes | E100: Supermercado | G100: 4290 | H100: =MONTH(Registros[[#This Row],[Fecha]]) -> 4 | I100: =YEAR(Registros[[#This Row],[Fecha]]) -> 2026 | J100: =OR(ISNUMBER(FIND("Sueldo",Registros[[#This Row],[Descripción]])),ISNUMBER(FIND("sueldo",Registros[[#This Row],[Descripción]]))) -> FALSE | K100: =OR(ISNUMBER(FIND("Javi",Registros[[#This Row],[Descripción]])),ISNUMBER(FIND("javi",Registros[[#This Row],[Descripción]]))) -> FALSE
B101: 46117 | C101: Jardin teresa | D101: Deseos | G101: 5000 | H101: =MONTH(Registros[[#This Row],[Fecha]]) -> 4 | I101: =YEAR(Registros[[#This Row],[Fecha]]) -> 2026 | J101: =OR(ISNUMBER(FIND("Sueldo",Registros[[#This Row],[Descripción]])),ISNUMBER(FIND("sueldo",Registros[[#This Row],[Descripción]]))) -> FALSE | K101: =OR(ISNUMBER(FIND("Javi",Registros[[#This Row],[Descripción]])),ISNUMBER(FIND("javi",Registros[[#This Row],[Descripción]]))) -> FALSE
...
